[
  {
    "id": 1,
    "title": "MAIN TITLE",
    "subtitle": "TEXT TEXT TEXT",
    "smallSubtitle": "TEXT TEXT TEXT TEXT",
    "src": "/images/mountains.jpg",
    "alt": "Mountains",
    "paddingTop": "30vh",
    "zIndex": 1,
    "offsetValue": 0.2
  },
  {
    "id": 2,
    "title": "MAIN TITLE",
    "subtitle": "TEXT TEXT TEXT",
    "smallSubtitle": "TEXT TEXT TEXT TEXT",
    "src": "/images/burger.jpg",
    "alt": "Burger",
    "paddingTop": "50vh",
    "zIndex": 2,
    "offsetValue": 0.05
  },
  {
    "id": 3,
    "title": "MAIN TITLE",
    "subtitle": "TEXT TEXT TEXT",
    "smallSubtitle": "TEXT TEXT TEXT TEXT",
    "backgroundColor": "blue",
    "paddingTop": "50vh",
    "zIndex": 3,
    "offsetValue": -0.05
  },
  {
    "id": 4,
    "title": "MAIN TITLE",
    "subtitle": "TEXT TEXT TEXT",
    "smallSubtitle": "TEXT TEXT TEXT TEXT",
    "backgroundColor": "pink",
    "paddingTop": "50vh",
    "zIndex": 4,
    "offsetValue": -0.06
  }
]